file_monitoring/__init__.py
file_monitoring/monitor.py
tests/__init__.py
tests/test_monitor.py
file_monitoring-0.1.0.dist-info/LICENSE
file_monitoring-0.1.0.dist-info/METADATA
file_monitoring-0.1.0.dist-info/WHEEL
file_monitoring-0.1.0.dist-info/entry_points.txt
file_monitoring-0.1.0.dist-info/top_level.txt
file_monitoring-0.1.0.dist-info/RECORD
