Metadata-Version: 2.1
Name: file_monitoring
Version: 0.1.0
Summary: A Python package for monitoring file changes and writing contents to a .txt file
Home-page: https://github.com/yourusername/file_monitoring
Author: Your Name
Author-email: your.email@example.com
Classifier: Programming Language :: Python :: 3
Classifier: License :: OSI Approved :: MIT License
Classifier: Operating System :: OS Independent
Requires-Python: >=3.6
License-File: LICENSE
Requires-Dist: watchdog
